{
  "name": "PHPCloud",
  "revision": "2013-07-05T17:47:54+02:00",
  "vendor_verified": false,
  "url": "http://www.phpcloud.com/",
  "status": "beta",
  "status_since": "2011-10-18",
  "type": "language-specific",
  "hosting": [
    "public",
    "private"
  ],
  "pricing": null,
  "scaling": {
    "vertical": false,
    "horizontal": false,
    "auto": true
  },
  "compliance": [

  ],
  "runtimes": [
    {
      "language": "php",
      "versions": [

      ]
    }
  ],
  "frameworks": null,
  "services": null,
  "extendable": false,
  "infrastructures": [
    {
      "continent": "NA",
      "country": "",
      "region": ""
    }
  ]
}